secmeta/__init__.py
secmeta/api.py
secmeta/cli.py
secmeta/fetch.py
secmeta/mapping.py
secmeta-0.1.0.dist-info/METADATA
secmeta-0.1.0.dist-info/WHEEL
secmeta-0.1.0.dist-info/entry_points.txt
secmeta-0.1.0.dist-info/top_level.txt
secmeta-0.1.0.dist-info/RECORD
