Metadata-Version: 2.4
Name: secmeta
Version: 0.1.0
Summary: A package for fetching SEC filings data
Author-email: Philipp Groegor <philipp.groegor+sectool@gmail.com>
License: MIT
Project-URL: Homepage, https://github.com/groegor/secmeta
Project-URL: Bug Tracker, https://github.com/groegor/secmeta/issues
Keywords: sec,edgar,filings,finance,accounting,accounting research,proxy filings
Classifier: Programming Language :: Python :: 3
Classifier: License :: OSI Approved :: MIT License
Classifier: Operating System :: OS Independent
Requires-Python: >=3.8
Requires-Dist: pandas
Requires-Dist: requests
